cisco_telnet.py
cisco_telnet-0.1.1.dist-info/METADATA
cisco_telnet-0.1.1.dist-info/WHEEL
cisco_telnet-0.1.1.dist-info/RECORD
