Metadata-Version: 2.3
Name: cisco_telnet
Version: 0.1.1
Summary: A Python module for applying Telnet configurations to Cisco devices.
License: MIT
Author: Yaroslav WWFyb3NsYXYg
Author-email: minestrim13@gmail.com
Requires-Python: >=3.11,<4.0
Classifier: License :: OSI Approved :: MIT License
Classifier: Programming Language :: Python :: 3
Classifier: Programming Language :: Python :: 3.11
Classifier: Programming Language :: Python :: 3.12
Classifier: Programming Language :: Python :: 3.13
Requires-Dist: asyncio (>=3.4.3,<4.0.0)
Requires-Dist: telnetlib3 (>=2.0.4,<3.0.0)
